README.rst
pulsar-script
setup.py
mpifr/__init__.py
mpifr.pulsarscript.egg-info/PKG-INFO
mpifr.pulsarscript.egg-info/SOURCES.txt
mpifr.pulsarscript.egg-info/dependency_links.txt
mpifr.pulsarscript.egg-info/top_level.txt
mpifr/pulsarscript/__init__.py
mpifr/pulsarscript/backend.py
mpifr/pulsarscript/bunch.py
mpifr/pulsarscript/config.py
mpifr/pulsarscript/mask.py
mpifr/pulsarscript/masknew.py
mpifr/pulsarscript/utils.py