Metadata-Version: 1.1
Name: mpifr.pulsarscript
Version: 0.0.3
Summary: Radioastronomic workflow service scripts
Home-page: https://bitbucket.org/mpifr/mpifr-pulsar-scripts
Author: Pavel Kretov
Author-email: firegurafiku@gmail.com
License: MIT
Keywords: command line
Platform: UNKNOWN
Classifier: Programming Language :: Python :: 3
Classifier: Development Status :: 2 - Pre-Alpha
Classifier: Environment :: Console
Classifier: Intended Audience :: Science/Research
Classifier: License :: OSI Approved :: MIT License
Classifier: Natural Language :: English
Classifier: Operating System :: POSIX
Classifier: Topic :: Software Development :: Libraries :: Python Modules
